README.rst
setup.py
yolog/__init__.py
yolog/config_handler.py
yolog/main.py
yolog/yolog_generator.py
yolog.egg-info/PKG-INFO
yolog.egg-info/SOURCES.txt
yolog.egg-info/dependency_links.txt
yolog.egg-info/entry_points.txt
yolog.egg-info/top_level.txt
yolog.egg-info/zip-safe