Metadata-Version: 1.0
Name: yolog
Version: 0.3
Summary: Beautify your Git Logs !
Home-page: https://www.github.com/karandesai-96/yolog
Author: Karan Desai
Author-email: karandesai281196@gmail.com
License: MIT
Platform: UNKNOWN
